{"cameraMode":{"drawMode":0,"name":"Shaded","section":"Shading Mode"},"sceneLighting":true,"audioPlay":false,"sceneViewState":{"showFog":true,"showMaterialUpdate":false,"showSkybox":true,"showFlares":true,"showImageEffects":true,"showParticleSystems":true},"in2DMode":false,"pivot":{"x":0.12385916709899903,"y":0.6525919437408447,"z":-0.10030031204223633},"rotation":{"x":-0.05057356134057045,"y":0.941003143787384,"z":-0.16279847919940949,"w":-0.2923229932785034},"size":6.904728889465332,"orthographic":false}